cauldron/__init__.py
cauldron/settings.json
cauldron/templating.py
cauldron/writer.py
cauldron/cli/__init__.py
cauldron/cli/batcher.py
cauldron/cli/commander.py
cauldron/cli/parse.py
cauldron/cli/shell.py
cauldron/cli/threads.py
cauldron/cli/commands/__init__.py
cauldron/cli/commands/alias.py
cauldron/cli/commands/cd.py
cauldron/cli/commands/clear.py
cauldron/cli/commands/close.py
cauldron/cli/commands/connect.py
cauldron/cli/commands/disconnect.py
cauldron/cli/commands/exit.py
cauldron/cli/commands/export.py
cauldron/cli/commands/ls.py
cauldron/cli/commands/purge.py
cauldron/cli/commands/refresh.py
cauldron/cli/commands/reload.py
cauldron/cli/commands/save.py
cauldron/cli/commands/show.py
cauldron/cli/commands/status.py
cauldron/cli/commands/sync.py
cauldron/cli/commands/ui.py
cauldron/cli/commands/version.py
cauldron/cli/commands/view.py
cauldron/cli/commands/configure/__init__.py
cauldron/cli/commands/configure/actions.py
cauldron/cli/commands/create/__init__.py
cauldron/cli/commands/create/actions.py
cauldron/cli/commands/listing/__init__.py
cauldron/cli/commands/listing/_lister.py
cauldron/cli/commands/listing/_remover.py
cauldron/cli/commands/listing/_utils.py
cauldron/cli/commands/listing/discovery.py
cauldron/cli/commands/open/__init__.py
cauldron/cli/commands/open/actions.py
cauldron/cli/commands/open/opener.py
cauldron/cli/commands/open/remote.py
cauldron/cli/commands/run/__init__.py
cauldron/cli/commands/run/actions.py
cauldron/cli/commands/steps/__init__.py
cauldron/cli/commands/steps/actions.py
cauldron/cli/commands/steps/removal.py
cauldron/cli/commands/steps/renaming.py
cauldron/cli/commands/steps/selection.py
cauldron/cli/commands/sync/__init__.py
cauldron/cli/commands/sync/syncer.py
cauldron/cli/interaction/__init__.py
cauldron/cli/interaction/autocompletion.py
cauldron/cli/interaction/query.py
cauldron/cli/server/__init__.py
cauldron/cli/server/arguments.py
cauldron/cli/server/authorization.py
cauldron/cli/server/run.py
cauldron_notebook-1.0.9.dist-info/LICENSE
cauldron_notebook-1.0.9.dist-info/METADATA
cauldron_notebook-1.0.9.dist-info/WHEEL
cauldron_notebook-1.0.9.dist-info/entry_points.txt
cauldron_notebook-1.0.9.dist-info/top_level.txt
cauldron_notebook-1.0.9.dist-info/RECORD
