Metadata-Version: 2.1
Name: cauldron-notebook
Version: 1.0.9
Summary: The Unnotebook: Data Analysis Environment
Home-page: https://github.com/sernst/cauldron
Author: Scott Ernst
Author-email: swernst@gmail.com
License: MIT
Keywords: Data,Analysis,Visualization,Interactive,Interpreter,Shell
Platform: Linux
Platform: Mac OS X
Platform: Windows
Classifier: Development Status :: 4 - Beta
Classifier: License :: OSI Approved :: MIT License
Classifier: Programming Language :: Python
Classifier: Programming Language :: Python :: 3.7
Classifier: Programming Language :: Python :: 3.8
Classifier: Programming Language :: Python :: 3.9
Classifier: Programming Language :: Python :: 3.10
Classifier: Intended Audience :: Developers
Classifier: Intended Audience :: System Administrators
Classifier: Intended Audience :: Science/Research
Classifier: Topic :: Scientific/Engineering
Classifier: Topic :: Scientific/Engineering :: Mathematics
Classifier: Topic :: Scientific/Engineering :: Visualization
Classifier: Topic :: Scientific/Engineering :: Information Analysis
License-File: LICENSE
Requires-Dist: pandas
Requires-Dist: numpy
Requires-Dist: jinja2
Requires-Dist: markdown
Requires-Dist: pygments
Requires-Dist: beautifulsoup4
Requires-Dist: flask
Requires-Dist: requests
Requires-Dist: waitress
Provides-Extra: bokeh
Requires-Dist: bokeh ; extra == 'bokeh'
Provides-Extra: matplotlib
Requires-Dist: matplotlib ; extra == 'matplotlib'
Requires-Dist: beautifulsoup4 ; extra == 'matplotlib'
Provides-Extra: plotly
Requires-Dist: plotly ; extra == 'plotly'
Provides-Extra: plotting
Requires-Dist: plotly ; extra == 'plotting'
Requires-Dist: matplotlib ; extra == 'plotting'
Requires-Dist: beautifulsoup4 ; extra == 'plotting'
Requires-Dist: bokeh ; extra == 'plotting'
Requires-Dist: seaborn ; extra == 'plotting'
Provides-Extra: seaborn
Requires-Dist: seaborn ; extra == 'seaborn'
